huaweicloudsdklive/__init__.py
huaweicloudsdklive/v1/__init__.py
huaweicloudsdklive/v1/live_async_client.py
huaweicloudsdklive/v1/live_client.py
huaweicloudsdklive/v1/model/__init__.py
huaweicloudsdklive/v1/model/add_flow_outputs_request.py
huaweicloudsdklive/v1/model/app_quality_info.py
huaweicloudsdklive/v1/model/audio_selector_hls_selection.py
huaweicloudsdklive/v1/model/audio_selector_lang_selection.py
huaweicloudsdklive/v1/model/audio_selector_pid_selection.py
huaweicloudsdklive/v1/model/audio_selector_settings.py
huaweicloudsdklive/v1/model/batch_show_ip_belongs_request.py
huaweicloudsdklive/v1/model/batch_show_ip_belongs_response.py
huaweicloudsdklive/v1/model/callback_url.py
huaweicloudsdklive/v1/model/cdn_ip.py
huaweicloudsdklive/v1/model/cert_info_resp.py
huaweicloudsdklive/v1/model/ces_dims_item.py
huaweicloudsdklive/v1/model/ces_dims_item_display.py
huaweicloudsdklive/v1/model/ces_dims_item_display_id.py
huaweicloudsdklive/v1/model/ces_query_resp_query.py
huaweicloudsdklive/v1/model/check_domain_verification_info.py
huaweicloudsdklive/v1/model/check_domain_verification_request.py
huaweicloudsdklive/v1/model/check_domain_verification_response.py
huaweicloudsdklive/v1/model/create_domain_mapping_request.py
huaweicloudsdklive/v1/model/create_domain_mapping_response.py
huaweicloudsdklive/v1/model/create_domain_request.py
huaweicloudsdklive/v1/model/create_domain_response.py
huaweicloudsdklive/v1/model/create_flow_output_request.py
huaweicloudsdklive/v1/model/create_flow_output_response.py
huaweicloudsdklive/v1/model/create_flows_request.py
huaweicloudsdklive/v1/model/create_flows_request_body.py
huaweicloudsdklive/v1/model/create_flows_response.py
huaweicloudsdklive/v1/model/create_harvest_task_info_req.py
huaweicloudsdklive/v1/model/create_harvest_task_request.py
huaweicloudsdklive/v1/model/create_harvest_task_response.py
huaweicloudsdklive/v1/model/create_ott_channel_info_req.py
huaweicloudsdklive/v1/model/create_ott_channel_info_req_record_settings.py
huaweicloudsdklive-3.1.184.dist-info/METADATA
huaweicloudsdklive-3.1.184.dist-info/WHEEL
huaweicloudsdklive-3.1.184.dist-info/licenses/LICENSE
huaweicloudsdklive-3.1.184.dist-info/RECORD
